voicebox_pytorch/__init__.py
voicebox_pytorch/attend.py
voicebox_pytorch/data.py
voicebox_pytorch/optimizer.py
voicebox_pytorch/trainer.py
voicebox_pytorch/voicebox_pytorch.py
voicebox_pytorch-0.5.0.dist-info/LICENSE
voicebox_pytorch-0.5.0.dist-info/METADATA
voicebox_pytorch-0.5.0.dist-info/WHEEL
voicebox_pytorch-0.5.0.dist-info/top_level.txt
voicebox_pytorch-0.5.0.dist-info/RECORD
